linux_profile/__init__.py
linux_profile/main.py
linux_profile/base/__init__.py
linux_profile/base/action.py
linux_profile/base/command.py
linux_profile/base/error.py
linux_profile/base/file.py
linux_profile/base/request.py
linux_profile/base/search.py
linux_profile/base/settings.py
linux_profile/base/system.py
linux_profile/base/validator.py
linux_profile/commands/__init__.py
linux_profile/commands/account.py
linux_profile/commands/add.py
linux_profile/commands/config.py
linux_profile/commands/execute.py
linux_profile/commands/install.py
linux_profile/commands/list.py
linux_profile/commands/profile.py
linux_profile/commands/remove.py
linux_profile/commands/uninstall.py
linux_profile/handlers/__init__.py
linux_profile/handlers/alias.py
linux_profile/handlers/file.py
linux_profile/handlers/package.py
linux_profile/handlers/script.py
linux_profile/utils/__init__.py
linux_profile/utils/file.py
linux_profile/utils/text.py
linux_profile/validators/__init__.py
linux_profile/validators/input_account.py
linux_profile/validators/input_alias.py
linux_profile/validators/input_config.py
linux_profile/validators/input_file.py
linux_profile/validators/input_package.py
linux_profile/validators/input_profile.py
linux_profile/validators/input_script.py
linux_profile/validators/input_text.py
linuxp-1.0.20.dist-info/LICENSE
linuxp-1.0.20.dist-info/METADATA
linuxp-1.0.20.dist-info/WHEEL
linuxp-1.0.20.dist-info/entry_points.txt
linuxp-1.0.20.dist-info/top_level.txt
linuxp-1.0.20.dist-info/zip-safe
linuxp-1.0.20.dist-info/RECORD
